ocrtools/__init__.py
ocrtools/build.py
ocrtools/explore.py
ocrtools/load.py
ocrtools/organize.py
ocrtools/tk_selector.py
ocrtools-0.1.2.dist-info/LICENSE.txt
ocrtools-0.1.2.dist-info/METADATA
ocrtools-0.1.2.dist-info/WHEEL
ocrtools-0.1.2.dist-info/top_level.txt
ocrtools-0.1.2.dist-info/RECORD
