Metadata-Version: 2.1
Name: ocrtools
Version: 0.1.2
Summary: Tools for interpreting and generating new climate data
Home-page: https://github.com/andreschang/ocr-tools
Author: Andres Chang
Author-email: andresdanielchang@gmail.com
License: MIT
Platform: UNKNOWN
Requires-Python: >=3.0
Requires-Dist: numpy
Requires-Dist: matplotlib
Requires-Dist: pandas
Requires-Dist: xarray
Requires-Dist: geopy
Requires-Dist: scipy
